drop_needle
