Metadata-Version: 2.1
Name: drop-needle
Version: 0.2
Summary: Simulate probability of a needle crossing a line on a table after it fell on it
Author: Martin Draws
